LICENSE
README.rst
pyproject.toml
setup.py
lifx_photons_messages_generator.egg-info/PKG-INFO
lifx_photons_messages_generator.egg-info/SOURCES.txt
lifx_photons_messages_generator.egg-info/dependency_links.txt
lifx_photons_messages_generator.egg-info/entry_points.txt
lifx_photons_messages_generator.egg-info/requires.txt
lifx_photons_messages_generator.egg-info/top_level.txt
photons_messages_generator/__init__.py
photons_messages_generator/adjustments.py
photons_messages_generator/errors.py
photons_messages_generator/executor.py
photons_messages_generator/field_types.py
photons_messages_generator/generate.py
photons_messages_generator/helpers.py
photons_messages_generator/resolver.py
photons_messages_generator/src.py
photons_messages_generator/test_helpers.py