Metadata-Version: 2.1
Name: lifx-photons-messages-generator
Version: 0.6.8
Summary: Code for generating the photons_messages module
Home-page: http://github.com/delfick/photons-messages-generator
Author: Stephen Moore
Author-email: delfick755@gmail.com
License: MIT
Keywords: lifx photons
Platform: UNKNOWN
Provides-Extra: tests
License-File: LICENSE
